TimeConvert/__init__.py
TimeConvert/convert.py
TimeConvert/isoweek.py
TimeConvert/month.py
TimeConvert/quarter.py
TimeConvert/stopwatch.py
TimeConvert/week.py
TimeConvert-3.0.12.dist-info/METADATA
TimeConvert-3.0.12.dist-info/WHEEL
TimeConvert-3.0.12.dist-info/top_level.txt
TimeConvert-3.0.12.dist-info/RECORD
