Metadata-Version: 2.1
Name: TimeConvert
Version: 3.0.12
Summary: Time Convert for Humans™
Home-page: https://github.com/xxx-convert/TimeConvert
Author: Hackathon
Author-email: kimi.huang@brightcells.com
Classifier: License :: OSI Approved :: BSD License
Classifier: Programming Language :: Python
Classifier: Programming Language :: Python :: 3
Classifier: Programming Language :: Python :: 3.7
Classifier: Programming Language :: Python :: 3.8
Classifier: Programming Language :: Python :: 3.9
Classifier: Programming Language :: Python :: 3.10
Classifier: Topic :: Software Development :: Libraries :: Python Modules
Requires-Python: >=3.5
Requires-Dist: isoweek
Requires-Dist: python-dateutil (>=2.8.1)
Requires-Dist: tzlocal
